{
    "Paper": "https://github.com/snwh/paper-icon-theme",
    "Paper-Mono-Dark": "https://github.com/snwh/paper-icon-theme",
    "Numix-Circle": "https://github.com/numixproject/numix-core",
    "Numix-Circle-Light": "https://github.com/numixproject/numix-core",
    "Numix-Square": "https://github.com/numixproject/numix-core",
    "Numix-Square-Light": "https://github.com/numixproject/numix-core",
    "Papirus-Dark": "https://github.com/PapirusDevelopmentTeam/papirus-icon-theme",
    "Papirus-Light": "https://github.com/PapirusDevelopmentTeam/papirus-icon-theme",
    "Papirus": "https://github.com/PapirusDevelopmentTeam/papirus-icon-theme",
    "ePapirus": "https://github.com/PapirusDevelopmentTeam/papirus-icon-theme"
}
